<annotation><filename>n03222722_8934.jpg</filename><folder>users/yehbr//doors</folder><source><submittedBy>Bryanna Yeh</submittedBy></source><imagesize><nrows>768</nrows><ncols>1024</ncols></imagesize><object><name>door</name><deleted>0</deleted><verified>0</verified><occluded>no</occluded><attributes></attributes><parts><hasparts></hasparts><ispartof></ispartof></parts><date>25-Mar-2015 01:32:56</date><id>0</id><polygon><username>Bryanna</username><pt><x>467</x><y>2</y></pt><pt><x>529</x><y>766</y></pt><pt><x>1023</x><y>763</y></pt><pt><x>1022</x><y>4</y></pt></polygon></object></annotation>